[
    {
        "current_plan_item": "findout(?set([goal(perform(omelette_recipe_action)), goal(perform(fries_recipe_action))])",
        "semantic_expression": "request(omelette_recipe_action)",
        "alternative": {
            "visual_information": [
                {
                    "attribute": "name",
                    "type": "text/plain",
                    "value": "Omelette"
                },
                {
                    "attribute": "image",
                    "type": "image/jpeg",
                    "value": "https://cdn.shopify.com/s/files/1/0959/3126/articles/IMG_7317_900x.jpg?v=1565647306"
                }
            ]
        }
    },
    {
        "current_plan_item": "findout(?set([goal(perform(omelette_recipe_action)), goal(perform(fries_recipe_action))])",
        "semantic_expression": "request(fries_recipe_action)",
        "alternative": {
            "visual_information": [
                {
                    "attribute": "name",
                    "type": "text/plain",
                    "value": "French Fries"
                },
                {
                    "attribute": "image",
                    "type": "image/jpeg",
                    "value": "https://nypost.com/wp-content/uploads/sites/2/2018/08/istock-618214356.jpg?quality=75&strip=all&w=744"
                }
            ]
        }
    }
]